<?xml version="1.0" encoding="utf-8"?>
<Items>
  <Item name="" identifier="securityuniform" category="Equipment" tags="smallitem" fireproof="false" cargocontaineridentifier="metalcrate" description="" scale="0.5" impactsoundtag="impact_soft">
    <Price locationtype="Military" buyprice="50" />
    <Price locationtype="City" buyprice="50" />
    <Price locationtype="Outpost" buyprice="100" />
    <InventoryIcon texture="Content/Items/InventoryIconAtlas.png" sourcerect="256,320,64,64" origin="0.5,0.5" />
    <Sprite texture="Content/Items/Jobgear/MiscJobGear.png" sourcerect="2,77,195,78" depth="0.6" origin="0.5,0.5" />
    <Body width="100" height="50" density="30" friction="0.8" restitution="0.01" />
    <Wearable slots="Any,InnerClothes" msg="ItemMsgPickUpSelect" variants="3">
      <sprite name="Security Officer's Uniform Torso" texture="securityofficer_torso_[GENDER]_[VARIANT].png" limb="Torso" hidelimb="true" inherittexturescale="true" inheritorigin="true" inheritsourcerect="true" />
      <sprite name="Security Officer's Uniform Left Arm" texture="securityofficer_torso_[GENDER]_[VARIANT].png" limb="LeftArm" hidelimb="true" inherittexturescale="true" inheritorigin="true" inheritsourcerect="true" />
      <sprite name="Security Officer's Uniform Right Arm" texture="securityofficer_torso_[GENDER]_[VARIANT].png" limb="RightArm" hidelimb="true" inherittexturescale="true" inheritorigin="true" inheritsourcerect="true" />
      <sprite name="Security Officer's Uniform Right Lower Arm" texture="securityofficer_torso_[GENDER]_[VARIANT].png" limb="RightHand" hidelimb="false" inherittexturescale="true" inheritorigin="true" inheritsourcerect="true" />
      <sprite name="Security Officer's Uniform Left Lower Arm" texture="securityofficer_torso_[GENDER]_[VARIANT].png" limb="LeftHand" hidelimb="false" inherittexturescale="true" inheritorigin="true" inheritsourcerect="true" />
      <sprite name="Security Officer's Uniform Waist" texture="securityofficer_legs_[GENDER]_[VARIANT].png" limb="Waist" hidelimb="true" inherittexturescale="true" inheritorigin="true" inheritsourcerect="true" />
      <sprite name="Security Officer's Uniform Right Thigh" texture="securityofficer_legs_[GENDER]_[VARIANT].png" limb="RightThigh" hidelimb="true" inherittexturescale="true" inheritorigin="true" inheritsourcerect="true" />
      <sprite name="Security Officer's Uniform Left Thigh" texture="securityofficer_legs_[GENDER]_[VARIANT].png" limb="LeftThigh" hidelimb="true" inherittexturescale="true" inheritorigin="true" inheritsourcerect="true" />
      <sprite name="Security Officer's Uniform Right Leg" texture="securityofficer_legs_[GENDER]_[VARIANT].png" limb="RightLeg" hidelimb="true" inherittexturescale="true" inheritorigin="true" inheritsourcerect="true" />
      <sprite name="Security Officer's Uniform Left Leg" texture="securityofficer_legs_[GENDER]_[VARIANT].png" limb="LeftLeg" hidelimb="true" inherittexturescale="true" inheritorigin="true" inheritsourcerect="true" />
      <sprite name="Security Officer's Uniform Right Shoe" texture="securityofficer_legs_[GENDER]_[VARIANT].png" limb="RightFoot" hidelimb="true" inherittexturescale="true" inheritorigin="true" inheritsourcerect="true" />
      <sprite name="Security Officer's Uniform Left Shoe" texture="securityofficer_legs_[GENDER]_[VARIANT].png" limb="LeftFoot" hidelimb="true" inherittexturescale="true" inheritorigin="true" inheritsourcerect="true" />
      <damagemodifier armorsector="0.0,360.0" afflictiontypes="bleeding" damagemultiplier="0.9" damagesound="LimbArmor" deflectprojectiles="true" />
      <damagemodifier armorsector="0.0,360.0" afflictiontypes="burn" damagemultiplier="0.7" damagesound="LimbArmor" deflectprojectiles="true" />
    </Wearable>
  </Item>
  <Item name="" identifier="bodyarmor" category="Equipment" tags="smallitem" scale="0.35" cargocontaineridentifier="metalcrate" description="" impactsoundtag="impact_soft">
    <Upgrade gameversion="0.9.3.0" scale="0.35" />
    <Price locationtype="Military" buyprice="225" />
    <Price locationtype="City" buyprice="300" />
    <Price locationtype="Outpost" buyprice="500" />
    <Deconstruct time="40">
      <Item identifier="ballisticfiber" />
      <Item identifier="ballisticfiber" />
    </Deconstruct>
    <Fabricate suitablefabricators="fabricator" requiredtime="30">
      <RequiredItem identifier="ballisticfiber" />
      <RequiredItem identifier="ballisticfiber" />
    </Fabricate>
    <InventoryIcon texture="Content/Items/InventoryIconAtlas.png" sourcerect="960,256,64,64" origin="0.5,0.5" />
    <Sprite texture="SecurityVest.png" sourcerect="14,45,103,158" depth="0.6" />
    <Body radius="45" height="50" density="40" />
    <Wearable slots="Any,OuterClothes" msg="ItemMsgPickUpSelect">
      <damagemodifier afflictiontypes="burn" armorsector="0.0,360.0" damagemultiplier="0.9" />
      <damagemodifier afflictiontypes="damage" armorsector="0.0,360.0" damagemultiplier="0.3" bleedingmultiplier="0.3" damagesound="LimbArmor" deflectprojectiles="true" />
      <damagemodifier afflictiontypes="bleeding" armorsector="0.0,360.0" damagemultiplier="0.1" bleedingmultiplier="0.0" damagesound="LimbArmor" deflectprojectiles="true" />
      <sprite name="Security Vest" texture="SecurityVest.png" limb="Torso" hidelimb="true" inherittexturescale="true" inheritorigin="true" inheritsourcerect="true" />
    </Wearable>
  </Item>
  <Item name="" identifier="ballistichelmet" category="Equipment" tags="smallitem" cargocontaineridentifier="metalcrate" description="" impactsoundtag="impact_metal_heavy">
    <Price locationtype="Military" buyprice="125" />
    <Price locationtype="City" buyprice="150" />
    <Price locationtype="Outpost" buyprice="200" />
    <Deconstruct time="10">
      <Item identifier="ballisticfiber" />
    </Deconstruct>
    <Fabricate suitablefabricators="fabricator" requiredtime="20">
      <RequiredItem identifier="ballisticfiber" />
    </Fabricate>
    <InventoryIcon texture="Content/Items/InventoryIconAtlas.png" sourcerect="320,0,64,64" origin="0.5,0.5" />
    <Sprite name="Ballistic Helmet" texture="Content/Items/Jobgear/headgears.png" sourcerect="15,220,73,66" depth="0.6" origin="0.5,0.5" />
    <Body radius="15" density="50" />
    <Wearable slots="Any,Head" armorvalue="20.0" msg="ItemMsgPickUpSelect">
      <damagemodifier afflictiontypes="damage" armorsector="0.0,360.0" damagemultiplier="0.2" bleedingmultiplier="0.2" damagesound="LimbArmor" deflectprojectiles="true" />
      <damagemodifier afflictiontypes="bleeding" armorsector="0.0,360.0" damagemultiplier="0.1" bleedingmultiplier="0.0" damagesound="LimbArmor" deflectprojectiles="true" />
      <sprite name="Ballistic Helmet Wearable" texture="Content/Items/Jobgear/headgears.png" limb="Head" inheritlimbdepth="true" inherittexturescale="true" hidewearablesoftype="hair" sourcerect="15,220,73,66" origin="0.5,0.7" />
    </Wearable>
  </Item>
  <Item name="" identifier="handcuffs" category="Equipment" cargocontaineridentifier="metalcrate" tags="smallitem" impactsoundtag="impact_metal_light">
    <Price locationtype="Military" buyprice="50" />
    <Price locationtype="City" buyprice="100" />
    <Price locationtype="Outpost" buyprice="100" />
    <Deconstruct time="10">
      <Item identifier="steel" />
    </Deconstruct>
    <Fabricate suitablefabricators="fabricator" requiredtime="10">
      <RequiredSkill identifier="mechanical" level="20" />
      <RequiredItem identifier="steel" />
    </Fabricate>
    <InventoryIcon texture="Content/Items/InventoryIconAtlas.png" sourcerect="192,0,64,64" origin="0.5,0.5" />
    <Sprite texture="securitygear.png" sourcerect="0,59,33,24" depth="0.6" />
    <Body width="30" height="15" density="40" />
    <Wearable slots="Any,RightHand+LeftHand" msg="ItemMsgPickUpSelect" autoequipwhenfull="false">
      <sprite texture="securitygear.png" limb="RightHand" sourcerect="32,62,16,16" origin="0.5,-0.5" depth="0.01" />
      <sprite texture="securitygear.png" limb="LeftHand" sourcerect="32,62,16,16" origin="0.5,-0.5" depth="0.01" />
      <StatusEffect type="OnWearing" target="Character" lockhands="true" setvalue="true" />
    </Wearable>
  </Item>
  <!-- 
  <Item name="" identifier="riotshield" category="Equipment" tags="weapon" impactsoundtag="impact_metal_light">
    <Price locationtype="Military" buyprice="200" />
    <Price locationtype="City" buyprice="225" />
    <Price locationtype="Outpost" buyprice="225" />
    <Deconstruct time="10">
      <Item identifier="titaniumaluminiumalloy" />
    </Deconstruct>
    <Fabricate suitablefabricators="fabricator" requiredtime="10">
      <RequiredSkill identifier="mechanical" level="50" />
      <RequiredItem identifier="titaniumaluminiumalloy" />
    </Fabricate>
    <InventoryIcon texture="Content/Items/InventoryIconAtlas.png" sourcerect="640,320,64,64" />
    <Sprite texture="riotgear.png" sourcerect="31,54,27,147" origin="0.5,0.5" depth="0.55" />
    <Body width="40" height="145" density="30" />
    <Holdable slots="RightHand+LeftHand" aimpos="60,-30" holdpos="45,-30" handle1="-10,0" handle2="10,0" controlpose="true" blocksplayers="true" msg="ItemMsgPickUpSelect">
      <StatusEffect type="OnActive" target="Character" SpeedMultiplier="0.6" setvalue="true" />
    </Holdable>
  </Item> -->
</Items>