<?xml version="1.0" encoding="utf-8"?>
<Items>
  <Item name="Wire" identifier="wire" category="Electrical" Tags="smallitem,wire" spritecolor="210,215,218,255" InventoryIconColor="210,215,218,255" canbepicked="true" cargocontaineridentifier="metalcrate">
    <Price locationtype="City" buyprice="80" />
    <Price locationtype="Outpost" buyprice="80" />
    <Price locationtype="Research" buyprice="80" />
    <Price locationtype="Military" buyprice="80" />
    <Deconstruct time="5">
      <Item identifier="copperbar" />
    </Deconstruct>
    <InventoryIcon texture="Content/Items/InventoryIconAtlas.png" sourcerect="448,64,64,64" />
    <Sprite texture="signalcomp.png" depth="0.55" sourcerect="77,106,48,20" />
    <Body radius="7" width="30" density="30" />
    <Holdable slots="Any,RightHand,LeftHand" handle1="0,0" />
    <Wire />
  </Item>
  <Item name="Red Wire" identifier="redwire" category="Electrical" Tags="smallitem,wire" spritecolor="254,23,17,255" InventoryIconColor="254,23,17,255" canbepicked="true" cargocontaineridentifier="metalcrate">
    <Price locationtype="City" buyprice="5" />
    <Price locationtype="Outpost" buyprice="5" />
    <Price locationtype="Research" buyprice="5" />
    <Price locationtype="Military" buyprice="5" />
    <Deconstruct time="5">
      <Item identifier="copperbar" />
    </Deconstruct>
    <InventoryIcon texture="Content/Items/InventoryIconAtlas.png" sourcerect="448,64,64,64" />
    <Sprite texture="signalcomp.png" depth="0.55" sourcerect="77,106,48,20" />
    <Body radius="7" width="30" density="30" />
    <Holdable slots="Any,RightHand,LeftHand" handle1="0,0" />
    <Wire />
  </Item>
  <Item name="Blue Wire" identifier="bluewire" category="Electrical" Tags="smallitem,wire" spritecolor="51,121,173,255" InventoryIconColor="51,121,173,255" canbepicked="true" cargocontaineridentifier="metalcrate">
    <Price locationtype="City" buyprice="5" />
    <Price locationtype="Outpost" buyprice="5" />
    <Price locationtype="Research" buyprice="5" />
    <Price locationtype="Military" buyprice="5" />
    <Deconstruct time="5">
      <Item identifier="copperbar" />
    </Deconstruct>
    <InventoryIcon texture="Content/Items/InventoryIconAtlas.png" sourcerect="448,64,64,64" />
    <Sprite texture="signalcomp.png" depth="0.55" sourcerect="77,106,48,20" />
    <Body radius="7" width="30" density="30" />
    <Holdable slots="Any,RightHand,LeftHand" handle1="0,0" />
    <Wire />
  </Item>
  <Item name="Orange Wire" identifier="orangewire" category="Electrical" Tags="smallitem,wire" spritecolor="255,140,13,255" InventoryIconColor="255,140,13,255" canbepicked="true" cargocontaineridentifier="metalcrate">
    <Price locationtype="City" buyprice="5" />
    <Price locationtype="Outpost" buyprice="5" />
    <Price locationtype="Research" buyprice="5" />
    <Price locationtype="Military" buyprice="5" />
    <Deconstruct time="5">
      <Item identifier="copperbar" />
    </Deconstruct>
    <InventoryIcon texture="Content/Items/InventoryIconAtlas.png" sourcerect="448,64,64,64" />
    <Sprite texture="signalcomp.png" depth="0.55" sourcerect="77,106,48,20" />
    <Body radius="7" width="30" density="30" />
    <Holdable slots="Any,RightHand,LeftHand" handle1="0,0" />
    <Wire />
  </Item>
  <Item name="Green Wire" identifier="greenwire" category="Electrical" Tags="smallitem,wire" spritecolor="56,143,111,255" InventoryIconColor="56,143,111,255" canbepicked="true" cargocontaineridentifier="metalcrate" price="10">
    <Price locationtype="City" buyprice="5" />
    <Price locationtype="Outpost" buyprice="5" />
    <Price locationtype="Research" buyprice="5" />
    <Price locationtype="Military" buyprice="5" />
    <Deconstruct time="5">
      <Item identifier="copperbar" />
    </Deconstruct>
    <InventoryIcon texture="Content/Items/InventoryIconAtlas.png" sourcerect="448,64,64,64" />
    <Sprite texture="signalcomp.png" depth="0.55" sourcerect="77,106,48,20" />
    <Body radius="7" width="30" density="30" />
    <Holdable slots="Any,RightHand,LeftHand" handle1="0,0" />
    <Wire />
  </Item>
  <Item name="Black Wire" identifier="blackwire" category="Electrical" Tags="smallitem,wire" spritecolor="50,50,50,255" InventoryIconColor="50,50,50,255" canbepicked="true" cargocontaineridentifier="metalcrate" price="10">
    <Price locationtype="City" buyprice="5" />
    <Price locationtype="Outpost" buyprice="5" />
    <Price locationtype="Research" buyprice="5" />
    <Price locationtype="Military" buyprice="5" />
    <Deconstruct time="5">
      <Item identifier="copperbar" />
    </Deconstruct>
    <InventoryIcon texture="Content/Items/InventoryIconAtlas.png" sourcerect="448,64,64,64" />
    <Sprite texture="signalcomp.png" depth="0.55" sourcerect="77,106,48,20" />
    <Body radius="7" width="30" density="30" />
    <Holdable slots="Any,RightHand,LeftHand" handle1="0,0" />
    <Wire />
  </Item>
  <Item name="Brown Wire" identifier="brownwire" category="Electrical" Tags="smallitem,wire" spritecolor="123,77,62,255" InventoryIconColor="123,77,62,255" canbepicked="true" cargocontaineridentifier="metalcrate" price="10">
    <Price locationtype="City" buyprice="5" />
    <Price locationtype="Outpost" buyprice="5" />
    <Price locationtype="Research" buyprice="5" />
    <Price locationtype="Military" buyprice="5" />
    <Deconstruct time="5">
      <Item identifier="copperbar" />
    </Deconstruct>
    <InventoryIcon texture="Content/Items/InventoryIconAtlas.png" sourcerect="448,64,64,64" />
    <Sprite texture="signalcomp.png" depth="0.55" sourcerect="77,106,48,20" />
    <Body radius="7" width="30" density="30" />
    <Holdable slots="Any,RightHand,LeftHand" handle1="0,0" />
    <Wire />
  </Item>
  <Item name="FPGA Circuit" identifier="fpgacircuit" category="Electrical" Tags="smallitem" cargocontaineridentifier="metalcrate" description="Field-programmable gate array - a multi-purpose circuit which can be reconfigured for use in a large variety of electrical devices.">
    <Price locationtype="Research" buyprice="20" />
    <Price locationtype="City" buyprice="25" />
    <Price locationtype="Outpost" buyprice="25" />
    <Price locationtype="Military" buyprice="25" />
    <Deconstruct time="5">
      <Item identifier="copperbar" />
      <Item identifier="copperbar" />
    </Deconstruct>
    <InventoryIcon texture="Content/Items/InventoryIconAtlas.png" sourcerect="512,64,64,64" />
    <Sprite texture="signalcomp.png" depth="0.8" sourcerect="32,16,16,16" />
    <Body width="16" height="16" density="30" />
    <Holdable slots="Any,RightHand,LeftHand" />
  </Item>
  <Item name="And Component" identifier="andcomponent" category="Electrical" Tags="smallitem" cargocontaineridentifier="metalcrate" description="Sends a signal when both inputs receive a signal within a set period of each other.">
    <Price locationtype="Research" buyprice="50" />
    <Price locationtype="City" buyprice="80" />
    <Price locationtype="Outpost" buyprice="80" />
    <Price locationtype="Military" buyprice="80" />
    <Deconstruct time="10">
      <Item identifier="steelbar" />
      <Item identifier="fpgacircuit" />
    </Deconstruct>
    <InventoryIcon texture="Content/Items/InventoryIconAtlas.png" sourcerect="64,384,64,64"/>
    <Sprite texture="signalcomp.png" depth="0.8" sourcerect="0,0,16,16" />
    <AndComponent canbeselected="true" />
    <Body width="16" height="16" density="30" />
    <Holdable selectkey="Select" pickkey="Use" slots="Any,RightHand,LeftHand" msg="ItemMsgDetachWrench" PickingTime="5.0" aimpos="65,-10" handle1="0,0" attachable="true" aimable="true">
      <RequiredItem identifier="wrench" type="Equipped" />
    </Holdable>
    <ConnectionPanel selectkey="Action" canbeselected="true" msg="ItemMsgRewireScrewdriver" hudpriority="10">
      <GuiFrame relativesize="0.2,0.32" minsize="400,350" maxsize="480,420" anchor="Center" style="ConnectionPanel" />
      <RequiredItem identifier="screwdriver,Wire" type="Equipped" />
      <input name="signal_in1" />
      <input name="signal_in2" />
      <input name="set_output" />
      <output name="signal_out" />
    </ConnectionPanel>
  </Item>
  <Item name="Adder Component" identifier="addercomponent" category="Electrical" Tags="smallitem" linkable="false" cargocontaineridentifier="metalcrate" price="10" description="Outputs the sum of the received signals.">
    <Price locationtype="Research" buyprice="50" />
    <Price locationtype="City" buyprice="80" />
    <Price locationtype="Outpost" buyprice="80" />
    <Price locationtype="Military" buyprice="80" />
    <Deconstruct time="10">
      <Item identifier="steelbar" />
      <Item identifier="fpgacircuit" />
    </Deconstruct>
    <InventoryIcon texture="Content/Items/InventoryIconAtlas.png" sourcerect="256,384,64,64"/>
    <Sprite texture="signalcomp.png" depth="0.8" sourcerect="17,80,16,16" />
    <AdderComponent canbeselected="true" />
    <Body width="16" height="16" density="30" />
    <Holdable selectkey="Select" pickkey="Use" slots="Any,RightHand,LeftHand" msg="ItemMsgDetachWrench" PickingTime="5.0" aimpos="65,-10" handle1="0,0" attachable="true" aimable="true">
      <RequiredItem identifier="wrench" type="Equipped" />
    </Holdable>
    <ConnectionPanel selectkey="Action" canbeselected="true" msg="ItemMsgRewireScrewdriver" hudpriority="10">
      <GuiFrame relativesize="0.2,0.32" minsize="400,350" maxsize="480,420" anchor="Center" style="ConnectionPanel" />
      <RequiredItem identifier="screwdriver,Wire" type="Equipped" />
      <input name="signal_in1" />
      <input name="signal_in2" />
      <output name="signal_out" />
    </ConnectionPanel>
  </Item>
  <Item name="Or Component" identifier="orcomponent" category="Electrical" Tags="smallitem" cargocontaineridentifier="metalcrate" description="Sends a signal if either of the inputs receive a signal.">
    <Price locationtype="Research" buyprice="50" />
    <Price locationtype="City" buyprice="80" />
    <Price locationtype="Outpost" buyprice="80" />
    <Price locationtype="Military" buyprice="80" />
    <Deconstruct time="10">
      <Item identifier="steelbar" />
      <Item identifier="fpgacircuit" />
    </Deconstruct>
    <InventoryIcon texture="Content/Items/InventoryIconAtlas.png" sourcerect="128,384,64,64"/>
    <Sprite texture="signalcomp.png" depth="0.8" sourcerect="16,0,16,16" />
    <OrComponent canbeselected="true" />
    <Body width="16" height="16" density="30" />
    <Holdable selectkey="Select" pickkey="Use" slots="Any,RightHand,LeftHand" msg="ItemMsgDetachWrench" PickingTime="5.0" aimpos="65,-10" handle1="0,0" attachable="true" aimable="true">
      <RequiredItem identifier="wrench" type="Equipped" />
    </Holdable>
    <ConnectionPanel selectkey="Action" canbeselected="true" msg="ItemMsgRewireScrewdriver" hudpriority="10">
      <GuiFrame relativesize="0.2,0.32" minsize="400,350" maxsize="480,420" anchor="Center" style="ConnectionPanel" />
      <RequiredItem identifier="screwdriver,Wire" type="Equipped" />
      <input name="signal_in1" />
      <input name="signal_in2" />
      <input name="set_output" />
      <output name="signal_out" />
    </ConnectionPanel>
  </Item>
  <Item name="Not Component" identifier="notcomponent" category="Electrical" Tags="smallitem" cargocontaineridentifier="metalcrate" description="Sends a signal when the input is NOT receiving a signal.">
    <Price locationtype="Research" buyprice="50" />
    <Price locationtype="City" buyprice="80" />
    <Price locationtype="Outpost" buyprice="80" />
    <Price locationtype="Military" buyprice="80" />
    <Deconstruct time="10">
      <Item identifier="steelbar" />
      <Item identifier="fpgacircuit" />
    </Deconstruct>
    <InventoryIcon texture="Content/Items/InventoryIconAtlas.png" sourcerect="192,384,64,64"/>
    <Sprite texture="signalcomp.png" depth="0.8" sourcerect="32,0,15,15" />
    <NotComponent canbeselected="true" />
    <Body width="16" height="16" density="30" />
    <Holdable selectkey="Select" pickkey="Use" slots="Any,RightHand,LeftHand" msg="ItemMsgDetachWrench" PickingTime="5.0" aimpos="65,-10" handle1="0,0" attachable="true" aimable="true">
      <RequiredItem identifier="wrench" type="Equipped" />
    </Holdable>
    <ConnectionPanel selectkey="Action" canbeselected="true" msg="ItemMsgRewireScrewdriver" hudpriority="10">
      <GuiFrame relativesize="0.2,0.32" minsize="400,350" maxsize="480,420" anchor="Center" style="ConnectionPanel" />
      <RequiredItem identifier="screwdriver,Wire" type="Equipped" />
      <input name="signal_in" />
      <output name="signal_out" />
    </ConnectionPanel>
  </Item>
  <Item name="Relay Component" identifier="relaycomponent" category="Electrical" Tags="smallitem" cargocontaineridentifier="metalcrate" description="When switched on, forwards all received signals from the input connections to the outputs.">
    <Price locationtype="Research" buyprice="50" />
    <Price locationtype="City" buyprice="80" />
    <Price locationtype="Outpost" buyprice="80" />
    <Price locationtype="Military" buyprice="80" />
    <Deconstruct time="10">
      <Item identifier="steelbar" />
      <Item identifier="fpgacircuit" />
    </Deconstruct>
    <InventoryIcon texture="Content/Items/InventoryIconAtlas.png" sourcerect="512,384,64,64"/>
    <Sprite texture="signalcomp.png" depth="0.8" sourcerect="48,16,16,16" />
    <RelayComponent canbeselected="true" vulnerabletoemp="false">
      <GuiFrame relativesize="0.2,0.15" minsize="350,160" maxsize="420,190" anchor="Center" style="ItemUI" />
    </RelayComponent>
    <Repairable selectkey="Action" name="Reset fuse" fixDurationHighSkill="1" fixDurationLowSkill="5" msg="ItemMsgRepairScrewdriver" hudpriority="10">
      <GuiFrame relativesize="0.2,0.16" minsize="400,180" maxsize="480,216" anchor="Center" relativeoffset="0.0,0.27" style="ItemUI" />
      <RequiredSkill identifier="electrical" level="40" />
      <RequiredItem identifier="screwdriver" type="equipped" />
    </Repairable>
    <Body width="16" height="16" density="30" />
    <Holdable selectkey="Select" pickkey="Use" slots="Any,RightHand,LeftHand" msg="ItemMsgDetachWrench" PickingTime="5.0" aimpos="65,-10" handle1="0,0" attachable="true" aimable="true">
      <RequiredItem identifier="wrench" type="Equipped" />
    </Holdable>
    <ConnectionPanel selectkey="Action" canbeselected="true" msg="ItemMsgRewireScrewdriver" hudpriority="10">
      <GuiFrame relativesize="0.2,0.32" minsize="400,350" maxsize="480,420" anchor="Center" style="ConnectionPanel" />
      <RequiredItem identifier="screwdriver,Wire" type="Equipped" />
      <input name="power_in" />
      <input name="signal_in1" />
      <input name="signal_in2" />
      <input name="toggle" />
      <input name="set_state" />
      <output name="power_out" />
      <output name="signal_out1" />
      <output name="signal_out2" />
      <output name="state_out" />
    </ConnectionPanel>
  </Item>
  <Item name="Delay Component" identifier="delaycomponent" category="Electrical" Tags="smallitem" cargocontaineridentifier="metalcrate" description="Delays all received signals for a specific amount of time.">
    <Price locationtype="Research" buyprice="50" />
    <Price locationtype="City" buyprice="80" />
    <Price locationtype="Outpost" buyprice="80" />
    <Price locationtype="Military" buyprice="80" />
    <Deconstruct time="10">
      <Item identifier="steelbar" />
      <Item identifier="fpgacircuit" />
    </Deconstruct>
    <InventoryIcon texture="Content/Items/InventoryIconAtlas.png" sourcerect="576,384,64,64"/>
    <Sprite texture="signalcomp.png" depth="0.8" sourcerect="16,35,16,16" />
    <DelayComponent canbeselected="true" />
    <Body width="16" height="8" density="30" />
    <Holdable selectkey="Select" pickkey="Use" slots="Any,RightHand,LeftHand" msg="ItemMsgDetachWrench" PickingTime="5.0" aimpos="65,-10" handle1="0,0" attachable="true" aimable="true">
      <RequiredItem identifier="wrench" type="Equipped" />
    </Holdable>
    <ConnectionPanel selectkey="Action" canbeselected="true" msg="ItemMsgRewireScrewdriver" hudpriority="10">
      <GuiFrame relativesize="0.2,0.32" minsize="400,350" maxsize="480,420" anchor="Center" style="ConnectionPanel" />
      <RequiredItem identifier="screwdriver,Wire" type="Equipped" />
      <input name="signal_in" />
      <output name="signal_out" />
    </ConnectionPanel>
  </Item>
  <Item name="Light Component" identifier="lightcomponent" category="Electrical" Tags="smallitem" cargocontaineridentifier="metalcrate">
    <Price locationtype="Research" buyprice="50" />
    <Price locationtype="City" buyprice="80" />
    <Price locationtype="Outpost" buyprice="80" />
    <Price locationtype="Military" buyprice="80" />
    <Deconstruct time="10">
      <Item identifier="steelbar" />
      <Item identifier="fpgacircuit" />
    </Deconstruct>
    <InventoryIcon texture="Content/Items/InventoryIconAtlas.png" sourcerect="959,128,64,64" />
    <Sprite texture="signalcomp.png" depth="0.8" sourcerect="48,0,16,16" />
    <LightComponent canbeselected="true" color="1.0,0.0,0.0,1.0" castshadows="false">
      <sprite texture="Content/Items/Electricity/signalcomp.png" sourcerect="0,96,31,32" />
    </LightComponent>
    <Body width="16" height="16" density="30" />
    <Holdable selectkey="Select" pickkey="Use" slots="Any,RightHand,LeftHand" msg="ItemMsgDetachWrench" PickingTime="5.0" aimpos="65,-10" handle1="0,0" attachable="true" aimable="true">
      <RequiredItem identifier="wrench" type="Equipped" />
    </Holdable>
    <ConnectionPanel selectkey="Action" canbeselected="true" msg="ItemMsgRewireScrewdriver" hudpriority="10">
      <GuiFrame relativesize="0.2,0.32" minsize="400,350" maxsize="480,420" anchor="Center" style="ConnectionPanel" />
      <RequiredItem identifier="screwdriver,Wire" type="Equipped" />
      <input name="toggle" />
      <input name="set_state" />
      <input name="set_color" />
    </ConnectionPanel>
  </Item>
  <Item name="Oxygen Detector" identifier="oxygendetector" category="Electrical" Tags="smallitem" cargocontaineridentifier="metalcrate" description="Sends out a value between 0-100 depending on the quality of the surrounding air.">
    <Price locationtype="Research" buyprice="50" />
    <Price locationtype="City" buyprice="80" />
    <Price locationtype="Outpost" buyprice="80" />
    <Price locationtype="Military" buyprice="80" />
    <Deconstruct time="10">
      <Item identifier="steelbar" />
      <Item identifier="fpgacircuit" />
    </Deconstruct>
    <InventoryIcon texture="Content/Items/InventoryIconAtlas.png" sourcerect="768,256,64,64" />
    <Sprite texture="signalcomp.png" depth="0.8" sourcerect="94,0,25,23" />
    <OxygenDetector canbeselected="true" />
    <Body width="31" height="24" density="30" />
    <Holdable selectkey="Select" pickkey="Use" slots="Any,RightHand,LeftHand" msg="ItemMsgDetachWrench" PickingTime="5.0" aimpos="65,-10" handle1="0,0" attachable="true" aimable="true">
      <RequiredItem identifier="wrench" type="Equipped" />
    </Holdable>
    <ConnectionPanel selectkey="Action" canbeselected="true" msg="ItemMsgRewireScrewdriver" hudpriority="10">
      <GuiFrame relativesize="0.2,0.32" minsize="400,350" maxsize="480,420" anchor="Center" style="ConnectionPanel" />
      <RequiredItem identifier="screwdriver,Wire" type="Equipped" />
      <output name="signal_out" />
    </ConnectionPanel>
  </Item>
  <Item name="Water Detector" identifier="waterdetector" category="Electrical" Tags="smallitem" cargocontaineridentifier="metalcrate" description="Sends out a signal when the detector is submerged.">
    <Price locationtype="Research" buyprice="50" />
    <Price locationtype="City" buyprice="80" />
    <Price locationtype="Outpost" buyprice="80" />
    <Price locationtype="Military" buyprice="80" />
    <Deconstruct time="10">
      <Item identifier="steelbar" />
      <Item identifier="fpgacircuit" />
    </Deconstruct>
    <InventoryIcon texture="Content/Items/InventoryIconAtlas.png" sourcerect="896,256,64,64" />
    <Sprite texture="signalcomp.png" depth="0.8" sourcerect="67,0,26,23" />
    <WaterDetector canbeselected="true" />
    <Body width="31" height="24" density="30" />
    <Holdable selectkey="Select" pickkey="Use" slots="Any,RightHand,LeftHand" msg="ItemMsgDetachWrench" PickingTime="5.0" aimpos="65,-10" handle1="0,0" attachable="true" aimable="true">
      <RequiredItem identifier="wrench" type="Equipped" />
    </Holdable>
    <ConnectionPanel selectkey="Action" canbeselected="true" msg="ItemMsgRewireScrewdriver" hudpriority="10">
      <GuiFrame relativesize="0.2,0.32" minsize="400,350" maxsize="480,420" anchor="Center" style="ConnectionPanel" />
      <RequiredItem identifier="screwdriver,Wire" type="Equipped" />
      <output name="signal_out" />
    </ConnectionPanel>
  </Item>
  <Item name="Smoke Detector" identifier="smokedetector" category="Electrical" Tags="smallitem" spritecolor="1.0,0.1,0.1,1.0" cargocontaineridentifier="metalcrate" description="Sends out a signal when it senses smoke.">
    <Price locationtype="Research" buyprice="50" />
    <Price locationtype="City" buyprice="80" />
    <Price locationtype="Outpost" buyprice="80" />
    <Price locationtype="Military" buyprice="80" />
    <Deconstruct time="10">
      <Item identifier="steelbar" />
      <Item identifier="fpgacircuit" />
    </Deconstruct>
    <Sprite texture="signalcomp.png" depth="0.8" sourcerect="67,0,26,23" />
    <SmokeDetector FireSizeThreshold="50" />
    <Body width="31" height="24" density="30" />
    <Holdable selectkey="Select" pickkey="Use" slots="Any,RightHand,LeftHand" msg="ItemMsgDetachWrench" PickingTime="5.0" aimpos="65,-10" handle1="0,0" attachable="true" aimable="true">
      <RequiredItem identifier="wrench" type="Equipped" />
    </Holdable>
    <ConnectionPanel selectkey="Action" canbeselected="true" msg="ItemMsgRewireScrewdriver" hudpriority="10">
      <GuiFrame relativesize="0.2,0.32" minsize="400,350" maxsize="480,420" anchor="Center" style="ConnectionPanel" />
      <RequiredItem identifier="screwdriver,Wire" type="Equipped" />
      <output name="signal_out" />
    </ConnectionPanel>
  </Item>
  <Item name="Motion Detector" identifier="motiondetector" category="Electrical" Tags="smallitem" cargocontaineridentifier="metalcrate" description="Sends out a signal when it detects movement.">
    <Price locationtype="Research" buyprice="50" />
    <Price locationtype="City" buyprice="80" />
    <Price locationtype="Outpost" buyprice="80" />
    <Price locationtype="Military" buyprice="80" />
    <Deconstruct time="10">
      <Item identifier="steelbar" />
      <Item identifier="fpgacircuit" />
    </Deconstruct>
    <InventoryIcon texture="Content/Items/InventoryIconAtlas.png" sourcerect="832,256,64,64" />
    <Sprite texture="signalcomp.png" depth="0.8" sourcerect="68,24,24,27" />
    <MotionSensor range="100" canbeselected="true" />
    <Body width="31" height="24" density="30" />
    <Holdable selectkey="Select" pickkey="Use" slots="Any,RightHand,LeftHand" msg="ItemMsgDetachWrench" PickingTime="5.0" aimpos="65,-10" handle1="0,0" attachable="true" aimable="true">
      <RequiredItem identifier="wrench" type="Equipped" />
    </Holdable>
    <ConnectionPanel selectkey="Action" canbeselected="true" msg="ItemMsgRewireScrewdriver" hudpriority="10">
      <GuiFrame relativesize="0.2,0.32" minsize="400,350" maxsize="480,420" anchor="Center" style="ConnectionPanel" />
      <RequiredItem identifier="screwdriver,Wire" type="Equipped" />
      <output name="state_out" />
    </ConnectionPanel>
  </Item>
  <Item name="Signal Check Component" identifier="signalcheckcomponent" category="Electrical" Tags="smallitem" cargocontaineridentifier="metalcrate" description="Sends a signal when a signal matching a specific value is received.">
    <Price locationtype="Research" buyprice="50" />
    <Price locationtype="City" buyprice="80" />
    <Price locationtype="Outpost" buyprice="80" />
    <Price locationtype="Military" buyprice="80" />
    <Deconstruct time="10">
      <Item identifier="steelbar" />
      <Item identifier="fpgacircuit" />
    </Deconstruct>
    <InventoryIcon texture="Content/Items/InventoryIconAtlas.png" sourcerect="448,384,64,64"/>
    <Sprite texture="signalcomp.png" depth="0.8" sourcerect="0,16,16,16" />
    <SignalCheckComponent canbeselected="true" />
    <Body width="16" height="16" density="30" />
    <Holdable selectkey="Select" pickkey="Use" slots="Any,RightHand,LeftHand" msg="ItemMsgDetachWrench" PickingTime="5.0" aimpos="65,-10" handle1="0,0" attachable="true" aimable="true">
      <RequiredItem identifier="wrench" type="Equipped" />
    </Holdable>
    <ConnectionPanel selectkey="Action" canbeselected="true" msg="ItemMsgRewireScrewdriver" hudpriority="10">
      <GuiFrame relativesize="0.2,0.32" minsize="400,350" maxsize="480,420" anchor="Center" style="ConnectionPanel" />
      <RequiredItem identifier="screwdriver,Wire" type="Equipped" />
      <input name="signal_in" />
      <input name="set_output" />
      <input name="set_targetsignal" />
      <output name="signal_out" />
    </ConnectionPanel>
  </Item>
  <Item name="RegEx Find Component" identifier="regexcomponent" category="Electrical" Tags="smallitem" cargocontaineridentifier="metalcrate" description="Sends a signal if the received signal matches a specific regular expression pattern.">
    <Price locationtype="Research" buyprice="50" />
    <Price locationtype="City" buyprice="80" />
    <Price locationtype="Outpost" buyprice="80" />
    <Price locationtype="Military" buyprice="80" />
    <Deconstruct time="10">
      <Item identifier="steelbar" />
      <Item identifier="fpgacircuit" />
    </Deconstruct>
    <InventoryIcon texture="Content/Items/InventoryIconAtlas.png" sourcerect="0,384,64,64"/>
    <Sprite texture="signalcomp.png" depth="0.8" sourcerect="16,16,16,16" />
    <RegExFindComponent canbeselected="true" />
    <Body width="16" height="16" density="30" />
    <Holdable selectkey="Select" pickkey="Use" aimpos="65,-10" handle1="0,0" attachable="true" aimable="true" PickingTime="5.0" slots="Any,RightHand,LeftHand" msg="ItemMsgDetachWrench">
      <RequiredItem identifier="wrench" type="Equipped" />
    </Holdable>
    <ConnectionPanel selectkey="Action" canbeselected="true" msg="ItemMsgRewireScrewdriver" hudpriority="10">
      <GuiFrame relativesize="0.2,0.32" minsize="400,350" maxsize="480,420" anchor="Center" style="ConnectionPanel" />
      <RequiredItem identifier="screwdriver,Wire" type="Equipped" />
      <input name="signal_in" />
      <output name="signal_out" />
    </ConnectionPanel>
  </Item>
  <Item name="Oscillator" identifier="oscillator" category="Electrical" Tags="smallitem" cargocontaineridentifier="metalcrate" description="Sends out a periodic, oscillating signal.">
    <Price locationtype="Research" buyprice="50" />
    <Price locationtype="City" buyprice="80" />
    <Price locationtype="Outpost" buyprice="80" />
    <Price locationtype="Military" buyprice="80" />
    <Deconstruct time="10">
      <Item identifier="steelbar" />
      <Item identifier="fpgacircuit" />
    </Deconstruct>
    <InventoryIcon texture="Content/Items/InventoryIconAtlas.png" sourcerect="320,384,64,64"/>
    <Sprite texture="signalcomp.png" depth="0.8" sourcerect="17,64,16,16" />
    <OscillatorComponent canbeselected="true" outputtype="Pulse" frequency="1" />
    <Body width="16" height="16" density="30" />
    <Holdable selectkey="Select" pickkey="Use" slots="Any,RightHand,LeftHand" msg="ItemMsgDetachWrench" PickingTime="5.0" aimpos="65,-10" handle1="0,0" attachable="true" aimable="true">
      <RequiredItem identifier="wrench" type="Equipped" />
    </Holdable>
    <ConnectionPanel selectkey="Action" canbeselected="true" msg="ItemMsgRewireScrewdriver" hudpriority="10">
      <GuiFrame relativesize="0.2,0.32" minsize="400,350" maxsize="480,420" anchor="Center" style="ConnectionPanel" />
      <RequiredItem identifier="screwdriver,Wire" type="Equipped" />
      <input name="set_frequency" />
      <input name="set_outputtype" />
      <output name="signal_out" />
    </ConnectionPanel>
  </Item>
  <Item name="Wifi Component" identifier="wificomponent" category="Electrical" Tags="smallitem" cargocontaineridentifier="metalcrate" description="Allows remote communication between other Wifi Components that are using the same channel.">
    <Price locationtype="Research" buyprice="50" />
    <Price locationtype="City" buyprice="80" />
    <Price locationtype="Outpost" buyprice="80" />
    <Price locationtype="Military" buyprice="80" />
    <Deconstruct time="10">
      <Item identifier="steelbar" />
      <Item identifier="fpgacircuit" />
    </Deconstruct>
    <InventoryIcon texture="Content/Items/InventoryIconAtlas.png" sourcerect="384,384,64,64"/>
    <Sprite texture="signalcomp.png" depth="0.8" sourcerect="0,35,16,16" />
    <WifiComponent canbeselected="true" MinChatMessageInterval="1.0" DiscardDuplicateChatMessages="true" />
    <Body width="16" height="16" density="30" />
    <Holdable selectkey="Select" pickkey="Use" aimpos="65,-10" handle1="0,0" attachable="true" aimable="true" PickingTime="5.0" slots="Any,RightHand,LeftHand" msg="ItemMsgDetachWrench">
      <RequiredItem identifier="wrench" type="Equipped" />
    </Holdable>
    <ConnectionPanel selectkey="Action" canbeselected="true" msg="ItemMsgRewireScrewdriver" hudpriority="10">
      <GuiFrame relativesize="0.2,0.32" minsize="400,350" maxsize="480,420" anchor="Center" style="ConnectionPanel" />
      <RequiredItem identifier="screwdriver,Wire" type="Equipped" />
      <input name="signal_in" />
      <output name="signal_out" />
    </ConnectionPanel>
  </Item>
  <Item name="Emergency Siren" identifier="emergencysiren" category="Electrical" Tags="smallitem" cargocontaineridentifier="metalcrate">
    <Price locationtype="Research" buyprice="50" />
    <Price locationtype="City" buyprice="80" />
    <Price locationtype="Outpost" buyprice="80" />
    <Price locationtype="Military" buyprice="80" />
    <Deconstruct time="10">
      <Item identifier="steelbar" />
      <Item identifier="fpgacircuit" />
    </Deconstruct>
    <InventoryIcon texture="Content/Items/InventoryIconAtlas.png" sourcerect="192,128,64,64" />
    <Sprite texture="signalcomp.png" depth="0.8" sourcerect="32,32,32,32" />
    <Body width="32" height="30" density="30" />
    <Holdable selectkey="Select" pickkey="Use" slots="Any,RightHand,LeftHand" msg="ItemMsgDetachWrench" PickingTime="5.0" aimpos="65,-10" handle1="0,0" attachable="true" aimable="true">
      <RequiredItem identifier="wrench" type="Equipped" />
    </Holdable>
    <ItemComponent>
      <sound file="Content/Items/warningSiren.ogg" type="OnActive" range="2000.0" loop="true" />
    </ItemComponent>
    <ConnectionPanel selectkey="Action" canbeselected="true" msg="ItemMsgRewireScrewdriver" hudpriority="10">
      <GuiFrame relativesize="0.2,0.32" minsize="400,350" maxsize="480,420" anchor="Center" style="ConnectionPanel" />
      <RequiredItem identifier="screwdriver,Wire" type="Equipped" />
      <input name="toggle" />
      <input name="set_state" />
    </ConnectionPanel>
  </Item>
  <Item name="Alarm Buzzer" identifier="alarmbuzzer" category="Electrical" Tags="smallitem" cargocontaineridentifier="metalcrate">
    <Price locationtype="Research" buyprice="50" />
    <Price locationtype="City" buyprice="80" />
    <Price locationtype="Outpost" buyprice="80" />
    <Price locationtype="Military" buyprice="80" />
    <Deconstruct time="10">
      <Item identifier="steelbar" />
      <Item identifier="fpgacircuit" />
    </Deconstruct>
    <InventoryIcon texture="Content/Items/InventoryIconAtlas.png" sourcerect="128,128,64,64" />
    <Sprite texture="signalcomp.png" depth="0.8" sourcerect="34,64,23,23" />
    <Body width="20" height="16" density="20" />
    <Holdable selectkey="Select" pickkey="Use" slots="Any,RightHand,LeftHand" msg="ItemMsgDetachWrench" PickingTime="5.0" aimpos="65,-10" handle1="0,0" attachable="true" aimable="true">
      <RequiredItem identifier="wrench" type="Equipped" />
    </Holdable>
    <ItemComponent>
      <sound file="Content/Items/warningBeep.ogg" type="OnActive" range="1000.0" loop="true" />
    </ItemComponent>
    <ConnectionPanel selectkey="Action" canbeselected="true" msg="ItemMsgRewireScrewdriver" hudpriority="10">
      <GuiFrame relativesize="0.2,0.32" minsize="400,350" maxsize="480,420" anchor="Center" style="ConnectionPanel" />
      <RequiredItem identifier="screwdriver,Wire" type="Equipped" />
      <input name="toggle" />
      <input name="set_state" />
    </ConnectionPanel>
  </Item>
  <Item name="Camera" identifier="camera" category="Electrical" Tags="smallitem" focusonselected="true" offsetonselected="500" cargocontaineridentifier="metalcrate" description="Typically used in photonics masts to provide the crew with a high-resolution view of the area outside the sub.">
    <Deconstruct time="10">
      <Item identifier="steelbar" />
      <Item identifier="fpgacircuit" />
    </Deconstruct>
    <Sprite texture="signalcomp.png" depth="0.8" sourcerect="0,64,16,32" />
    <ConnectionPanel selectkey="Action" canbeselected="true" msg="ItemMsgRewireScrewdriver" hudpriority="10">
      <GuiFrame relativesize="0.2,0.32" minsize="400,350" maxsize="480,420" anchor="Center" style="ConnectionPanel" />
      <RequiredItem identifier="screwdriver,Wire" type="Equipped" />
      <input name="control_in" />
    </ConnectionPanel>
  </Item>
</Items>